<?xml version="1.0" encoding="UTF-8"?>
<!DOCTYPE hibernate-mapping PUBLIC "-//Hibernate/Hibernate Mapping DTD 3.0//EN"
	"http://hibernate.sourceforge.net/hibernate-mapping-3.0.dtd">

<hibernate-mapping>
	<class name="cn.edustar.usermgr.pojos.Config" table="T_Config">
		<id name="id" type="int">
			<column name="Id" />
			<generator class="identity" />
		</id>
		<property name="key" type="java.lang.String">
			<column name="ConfigKey" length="50" not-null="true" />
		</property>
		<property name="value" type="java.lang.String">
			<column name="ConfigValue" length="50" not-null="true" />
		</property>
	</class>
</hibernate-mapping>
